{
  "timestamp": "2025-11-25T09:54:02.140726Z",
  "source": "CoinGecko API",
  "prices": {
    "BTC/USDC": {
      "price": 87019,
      "change_24h": 1.2388611707853174,
      "volume_24h": 72384640819.41959
    },
    "ETH/USDC": {
      "price": 2887.54,
      "change_24h": 3.2647897168029476,
      "volume_24h": 26800839280.933212
    },
    "BNB/USDC": {
      "price": 852.04,
      "change_24h": 1.3232577076540635,
      "volume_24h": 1767185083.6544106
    },
    "SOL/USDC": {
      "price": 135.78,
      "change_24h": 5.262365708009961,
      "volume_24h": 5533214233.618804
    },
    "ADA/USDC": {
      "price": 0.415881,
      "change_24h": 2.4181046618756024,
      "volume_24h": 692726366.138696
    },
    "DOGE/USDC": {
      "price": 0.148306,
      "change_24h": 2.6324707849313698,
      "volume_24h": 1513416154.4283738
    },
    "XRP/USDC": {
      "price": 2.2,
      "change_24h": 7.7264011990909705,
      "volume_24h": 6350949623.174412
    },
    "DOT/USDC": {
      "price": 2.27,
      "change_24h": 0.7581989750596614,
      "volume_24h": 201460799.52225164
    },
    "AVAX/USDC": {
      "price": 13.86,
      "change_24h": 4.146360393053914,
      "volume_24h": 418009684.9685391
    },
    "LINK/USDC": {
      "price": 12.78,
      "change_24h": 3.0523872687528852,
      "volume_24h": 656274213.4371787
    }
  }
}