{
  "timestamp": "2025-12-14T16:44:34.016823Z",
  "source": "CoinGecko API",
  "prices": {
    "BTC/USDC": {
      "price": 88984,
      "change_24h": -1.2095804232989453,
      "volume_24h": 32842873120.546043
    },
    "ETH/USDC": {
      "price": 3090.22,
      "change_24h": -0.45892312226518317,
      "volume_24h": 11987214135.797565
    },
    "BNB/USDC": {
      "price": 885.25,
      "change_24h": -1.8221956207468204,
      "volume_24h": 912351322.1572388
    },
    "SOL/USDC": {
      "price": 130.9,
      "change_24h": -1.6834175753174685,
      "volume_24h": 2468691296.3151584
    },
    "ADA/USDC": {
      "price": 0.399701,
      "change_24h": -3.108247515991543,
      "volume_24h": 471644575.51772
    },
    "DOGE/USDC": {
      "price": 0.135481,
      "change_24h": -2.7821177995210533,
      "volume_24h": 603231215.3499683
    },
    "XRP/USDC": {
      "price": 1.99,
      "change_24h": -1.5161409231673664,
      "volume_24h": 1368985000.5988886
    },
    "DOT/USDC": {
      "price": 1.98,
      "change_24h": -3.5318425661775685,
      "volume_24h": 128433725.7989722
    },
    "AVAX/USDC": {
      "price": 13.02,
      "change_24h": -2.5067655095139996,
      "volume_24h": 206099925.82579222
    },
    "LINK/USDC": {
      "price": 13.49,
      "change_24h": -2.0274277707673987,
      "volume_24h": 317548307.35419106
    }
  }
}