{
  "timestamp": "2026-04-18T21:00:39.272654Z",
  "source": "CoinGecko API",
  "prices": {
    "BTC/USDC": {
      "price": 75766,
      "change_24h": -2.091542325628398,
      "volume_24h": 63987384157.149895
    },
    "ETH/USDC": {
      "price": 2353.44,
      "change_24h": -3.148343419811285,
      "volume_24h": 15749905700.00925
    },
    "BNB/USDC": {
      "price": 630.6,
      "change_24h": -1.661037631133402,
      "volume_24h": 1032907729.3603797
    },
    "SOL/USDC": {
      "price": 86.22,
      "change_24h": -3.263658378675216,
      "volume_24h": 2883366791.0005016
    },
    "ADA/USDC": {
      "price": 0.249202,
      "change_24h": -4.579814070672085,
      "volume_24h": 398735541.495085
    },
    "DOGE/USDC": {
      "price": 0.095051,
      "change_24h": -5.154800350929116,
      "volume_24h": 1593626836.7364457
    },
    "XRP/USDC": {
      "price": 1.43,
      "change_24h": -3.666926963707178,
      "volume_24h": 2527490068.750416
    },
    "DOT/USDC": {
      "price": 1.28,
      "change_24h": -3.7781781053816896,
      "volume_24h": 191118476.99705628
    },
    "AVAX/USDC": {
      "price": 9.41,
      "change_24h": -3.7691177498888386,
      "volume_24h": 263559401.31955448
    },
    "LINK/USDC": {
      "price": 9.31,
      "change_24h": -3.4626533424015173,
      "volume_24h": 329477298.9292253
    }
  }
}