{
  "timestamp": "2025-12-27T08:20:20.395331Z",
  "source": "CoinGecko API",
  "prices": {
    "BTC/USDC": {
      "price": 87521,
      "change_24h": -1.2059647003100336,
      "volume_24h": 31868270290.995926
    },
    "ETH/USDC": {
      "price": 2932.87,
      "change_24h": -0.9763605172694411,
      "volume_24h": 12905945491.477327
    },
    "BNB/USDC": {
      "price": 840.94,
      "change_24h": -0.019102095060974718,
      "volume_24h": 911389847.6262057
    },
    "SOL/USDC": {
      "price": 123.19,
      "change_24h": 0.29662196188383905,
      "volume_24h": 3110168537.900149
    },
    "ADA/USDC": {
      "price": 0.352824,
      "change_24h": -0.03240630651349545,
      "volume_24h": 397284218.4529253
    },
    "DOGE/USDC": {
      "price": 0.122614,
      "change_24h": -2.5285294948819494,
      "volume_24h": 787968770.1084536
    },
    "XRP/USDC": {
      "price": 1.85,
      "change_24h": -0.9964397895799485,
      "volume_24h": 1612492225.8482738
    },
    "DOT/USDC": {
      "price": 1.75,
      "change_24h": 1.8271707248343274,
      "volume_24h": 113841553.37412032
    },
    "AVAX/USDC": {
      "price": 12.44,
      "change_24h": 0.207147569123543,
      "volume_24h": 198912590.2851663
    },
    "LINK/USDC": {
      "price": 12.25,
      "change_24h": -1.0430771159713828,
      "volume_24h": 252692360.42079636
    }
  }
}