{
  "timestamp": "2026-02-02T07:38:36.983803Z",
  "source": "CoinGecko API",
  "prices": {
    "BTC/USDC": {
      "price": 76452,
      "change_24h": -2.317174082754101,
      "volume_24h": 77615423945.07214
    },
    "ETH/USDC": {
      "price": 2230.36,
      "change_24h": -7.580223555663089,
      "volume_24h": 54182288054.86029
    },
    "BNB/USDC": {
      "price": 750.97,
      "change_24h": -3.154309917936483,
      "volume_24h": 2656262289.6360626
    },
    "SOL/USDC": {
      "price": 101.39,
      "change_24h": -3.0334645309960493,
      "volume_24h": 8552037830.159164
    },
    "ADA/USDC": {
      "price": 0.284658,
      "change_24h": -3.5414144846930653,
      "volume_24h": 870743640.5999696
    },
    "DOGE/USDC": {
      "price": 0.103163,
      "change_24h": -1.589285877443071,
      "volume_24h": 2172984124.239496
    },
    "XRP/USDC": {
      "price": 1.58,
      "change_24h": -4.236693246797363,
      "volume_24h": 5148284770.67654
    },
    "DOT/USDC": {
      "price": 1.5,
      "change_24h": -3.1023470839870773,
      "volume_24h": 202736985.67432508
    },
    "AVAX/USDC": {
      "price": 9.84,
      "change_24h": -3.040543858001728,
      "volume_24h": 472677825.57534987
    },
    "LINK/USDC": {
      "price": 9.37,
      "change_24h": -5.299032643657855,
      "volume_24h": 807339048.0122248
    }
  }
}