{
  "timestamp": "2026-01-13T08:24:40.786981Z",
  "source": "CoinGecko API",
  "prices": {
    "BTC/USDC": {
      "price": 91962,
      "change_24h": 0.6465489804662455,
      "volume_24h": 45057771782.68416
    },
    "ETH/USDC": {
      "price": 3125.15,
      "change_24h": -0.3671657156149529,
      "volume_24h": 22149664461.675323
    },
    "BNB/USDC": {
      "price": 909.73,
      "change_24h": 0.35003022583608767,
      "volume_24h": 1503979236.0493593
    },
    "SOL/USDC": {
      "price": 140.47,
      "change_24h": -0.8069913700845804,
      "volume_24h": 6446705843.026719
    },
    "ADA/USDC": {
      "price": 0.390708,
      "change_24h": -0.1658710643880594,
      "volume_24h": 550576909.8813014
    },
    "DOGE/USDC": {
      "price": 0.139024,
      "change_24h": 0.5025431175611416,
      "volume_24h": 1177469554.2939482
    },
    "XRP/USDC": {
      "price": 2.06,
      "change_24h": 0.17865244141368777,
      "volume_24h": 3070381935.5740557
    },
    "DOT/USDC": {
      "price": 2.08,
      "change_24h": 0.45054579853496346,
      "volume_24h": 134160464.39967659
    },
    "AVAX/USDC": {
      "price": 13.75,
      "change_24h": -0.04576063271718805,
      "volume_24h": 366793866.31547093
    },
    "LINK/USDC": {
      "price": 13.2,
      "change_24h": -0.7057945141504899,
      "volume_24h": 355809897.89268476
    }
  }
}