{
  "timestamp": "2026-02-16T19:02:34.366212Z",
  "source": "CoinGecko API",
  "prices": {
    "BTC/USDC": {
      "price": 67869,
      "change_24h": -0.6900303895868084,
      "volume_24h": 38953505487.55267
    },
    "ETH/USDC": {
      "price": 1969.1,
      "change_24h": 0.8423208699822369,
      "volume_24h": 21518221005.555428
    },
    "BNB/USDC": {
      "price": 614.74,
      "change_24h": 0.5275433478479753,
      "volume_24h": 848947064.9211818
    },
    "SOL/USDC": {
      "price": 84.6,
      "change_24h": -1.7286551732026354,
      "volume_24h": 3916018559.690823
    },
    "ADA/USDC": {
      "price": 0.281578,
      "change_24h": 0.9890529364059696,
      "volume_24h": 355796276.8258325
    },
    "DOGE/USDC": {
      "price": 0.100439,
      "change_24h": -3.475181669356603,
      "volume_24h": 1354865499.1453142
    },
    "XRP/USDC": {
      "price": 1.47,
      "change_24h": 0.4561558027952113,
      "volume_24h": 3449261940.233814
    },
    "DOT/USDC": {
      "price": 1.35,
      "change_24h": 1.1395639623143534,
      "volume_24h": 97602629.36153528
    },
    "AVAX/USDC": {
      "price": 9.13,
      "change_24h": -0.6237103294706808,
      "volume_24h": 220552803.6872253
    },
    "LINK/USDC": {
      "price": 8.76,
      "change_24h": 0.9950985559662114,
      "volume_24h": 270022897.39416164
    }
  }
}