{
  "timestamp": "2026-04-29T23:09:40.697696Z",
  "source": "CoinGecko API",
  "prices": {
    "BTC/USDC": {
      "price": 75876,
      "change_24h": -0.5214039104531184,
      "volume_24h": 42387942125.52455
    },
    "ETH/USDC": {
      "price": 2254.88,
      "change_24h": -1.4226144708194766,
      "volume_24h": 19403095981.436085
    },
    "BNB/USDC": {
      "price": 617.35,
      "change_24h": -0.9733632831271837,
      "volume_24h": 1055200004.4477105
    },
    "SOL/USDC": {
      "price": 82.96,
      "change_24h": -0.9682555835367774,
      "volume_24h": 3789514372.053677
    },
    "ADA/USDC": {
      "price": 0.243976,
      "change_24h": -1.1327686752561281,
      "volume_24h": 478560980.0256219
    },
    "DOGE/USDC": {
      "price": 0.103481,
      "change_24h": 4.065627261170505,
      "volume_24h": 4214010099.180921
    },
    "XRP/USDC": {
      "price": 1.37,
      "change_24h": -0.898808308397165,
      "volume_24h": 2255393718.1505113
    },
    "DOT/USDC": {
      "price": 1.21,
      "change_24h": -1.39100324847021,
      "volume_24h": 139318120.01455247
    },
    "AVAX/USDC": {
      "price": 9.1,
      "change_24h": -0.6106703814669392,
      "volume_24h": 237161476.27333805
    },
    "LINK/USDC": {
      "price": 9.1,
      "change_24h": -1.3685465592158117,
      "volume_24h": 259107500.1013818
    }
  }
}