{
  "timestamp": "2026-05-24T01:35:18.794324Z",
  "source": "CoinGecko API",
  "prices": {
    "BTC/USDC": {
      "price": 76810,
      "change_24h": 1.8891974283154065,
      "volume_24h": 32062488034.21333
    },
    "ETH/USDC": {
      "price": 2120.45,
      "change_24h": 2.6533545517116197,
      "volume_24h": 16186168085.095379
    },
    "BNB/USDC": {
      "price": 657.05,
      "change_24h": 0.9966586478419635,
      "volume_24h": 744935121.668644
    },
    "SOL/USDC": {
      "price": 86.03,
      "change_24h": 1.8365275383282587,
      "volume_24h": 3230172928.5261245
    },
    "ADA/USDC": {
      "price": 0.245767,
      "change_24h": 1.029083617599981,
      "volume_24h": 418076040.7754471
    },
    "DOGE/USDC": {
      "price": 0.103077,
      "change_24h": 1.5442309736924458,
      "volume_24h": 1000079151.460443
    },
    "XRP/USDC": {
      "price": 1.36,
      "change_24h": 1.8771570939382323,
      "volume_24h": 1778245659.1601698
    },
    "DOT/USDC": {
      "price": 1.29,
      "change_24h": 2.9865723123683594,
      "volume_24h": 168839175.84925577
    },
    "AVAX/USDC": {
      "price": 9.4,
      "change_24h": 2.656481662186152,
      "volume_24h": 254825723.84900537
    },
    "LINK/USDC": {
      "price": 9.59,
      "change_24h": 2.045889303880148,
      "volume_24h": 330989078.0830948
    }
  }
}