{
  "timestamp": "2026-06-29T16:27:02.739849Z",
  "source": "CoinGecko API",
  "prices": {
    "BTC/USDC": {
      "price": 59550,
      "change_24h": -0.17601141694384165,
      "volume_24h": 31237111278.666264
    },
    "ETH/USDC": {
      "price": 1572.89,
      "change_24h": -0.009317398284557155,
      "volume_24h": 10957772201.498545
    },
    "BNB/USDC": {
      "price": 550.22,
      "change_24h": -0.3621906050592854,
      "volume_24h": 759971640.0413965
    },
    "SOL/USDC": {
      "price": 73.17,
      "change_24h": 1.9642949980988558,
      "volume_24h": 3640665633.0387435
    },
    "ADA/USDC": {
      "price": 0.144889,
      "change_24h": 0.8429769153702136,
      "volume_24h": 301873027.68675333
    },
    "DOGE/USDC": {
      "price": 0.072438,
      "change_24h": -1.0380467696931033,
      "volume_24h": 587946984.2408562
    },
    "XRP/USDC": {
      "price": 1.044,
      "change_24h": -0.35293021111969963,
      "volume_24h": 1766296117.1319535
    },
    "DOT/USDC": {
      "price": 0.819241,
      "change_24h": 1.1925900449002786,
      "volume_24h": 90305261.37024735
    },
    "AVAX/USDC": {
      "price": 6.65,
      "change_24h": 5.58622935532428,
      "volume_24h": 267035344.70012763
    },
    "LINK/USDC": {
      "price": 7.3,
      "change_24h": 0.402927458708824,
      "volume_24h": 224248089.4198211
    }
  }
}