{
  "timestamp": "2026-06-12T01:42:55.244556Z",
  "source": "CoinGecko API",
  "prices": {
    "BTC/USDC": {
      "price": 63284,
      "change_24h": 1.6980361905715318,
      "volume_24h": 29915153187.11433
    },
    "ETH/USDC": {
      "price": 1661.82,
      "change_24h": 1.0873050674525322,
      "volume_24h": 11820517210.463976
    },
    "BNB/USDC": {
      "price": 601.12,
      "change_24h": 1.3369959693390046,
      "volume_24h": 674491938.3050996
    },
    "SOL/USDC": {
      "price": 66.48,
      "change_24h": 2.611809461256792,
      "volume_24h": 2777538860.8942695
    },
    "ADA/USDC": {
      "price": 0.169069,
      "change_24h": 3.773666107794508,
      "volume_24h": 490906764.10596794
    },
    "DOGE/USDC": {
      "price": 0.085574,
      "change_24h": 1.614863671938956,
      "volume_24h": 621652793.2861334
    },
    "XRP/USDC": {
      "price": 1.14,
      "change_24h": 2.129719619003626,
      "volume_24h": 1613945496.4719543
    },
    "DOT/USDC": {
      "price": 0.945856,
      "change_24h": 1.295686339539931,
      "volume_24h": 91801598.66797999
    },
    "AVAX/USDC": {
      "price": 6.61,
      "change_24h": 1.8130091495294667,
      "volume_24h": 185024958.7616005
    },
    "LINK/USDC": {
      "price": 7.85,
      "change_24h": 2.0275385366901038,
      "volume_24h": 263632990.8192039
    }
  }
}