{
  "timestamp": "2026-01-18T09:50:32.338437Z",
  "source": "CoinGecko API",
  "prices": {
    "BTC/USDC": {
      "price": 95225,
      "change_24h": -4.3353267414640964e-05,
      "volume_24h": 19026918761.58058
    },
    "ETH/USDC": {
      "price": 3319.89,
      "change_24h": 0.6148453023312436,
      "volume_24h": 11820372168.020054
    },
    "BNB/USDC": {
      "price": 945.2,
      "change_24h": 0.4402174001063416,
      "volume_24h": 1326141687.5980244
    },
    "SOL/USDC": {
      "price": 142.4,
      "change_24h": -1.3855017231807552,
      "volume_24h": 2387564091.448811
    },
    "ADA/USDC": {
      "price": 0.393781,
      "change_24h": -0.5538593303098721,
      "volume_24h": 331277958.17120904
    },
    "DOGE/USDC": {
      "price": 0.137418,
      "change_24h": -0.05962651671672849,
      "volume_24h": 576604527.3820422
    },
    "XRP/USDC": {
      "price": 2.06,
      "change_24h": -0.33044274519608197,
      "volume_24h": 1349494957.3558757
    },
    "DOT/USDC": {
      "price": 2.15,
      "change_24h": -1.4854962252176453,
      "volume_24h": 142390928.71917018
    },
    "AVAX/USDC": {
      "price": 13.64,
      "change_24h": -0.2623609017747232,
      "volume_24h": 202340296.12184578
    },
    "LINK/USDC": {
      "price": 13.8,
      "change_24h": 0.49357083602958995,
      "volume_24h": 228584664.95828196
    }
  }
}