{
  "timestamp": "2025-12-10T19:30:50.966644Z",
  "source": "CoinGecko API",
  "prices": {
    "BTC/USDC": {
      "price": 92433,
      "change_24h": -1.7069861007171439,
      "volume_24h": 46364872155.271286
    },
    "ETH/USDC": {
      "price": 3376.06,
      "change_24h": 0.09358588603903088,
      "volume_24h": 30340467310.08065
    },
    "BNB/USDC": {
      "price": 898.55,
      "change_24h": -1.9086066572311235,
      "volume_24h": 1760219447.4476035
    },
    "SOL/USDC": {
      "price": 138.21,
      "change_24h": -3.00657661816445,
      "volume_24h": 5971931815.194016
    },
    "ADA/USDC": {
      "price": 0.464002,
      "change_24h": -2.75246141106617,
      "volume_24h": 1057608994.230642
    },
    "DOGE/USDC": {
      "price": 0.147324,
      "change_24h": -2.5125385141072885,
      "volume_24h": 1247180416.4701378
    },
    "XRP/USDC": {
      "price": 2.07,
      "change_24h": -3.280920777883748,
      "volume_24h": 3713663146.1830683
    },
    "DOT/USDC": {
      "price": 2.26,
      "change_24h": -2.9195014189657695,
      "volume_24h": 183760177.46974307
    },
    "AVAX/USDC": {
      "price": 14.49,
      "change_24h": -0.8820903757647988,
      "volume_24h": 400202877.45021284
    },
    "LINK/USDC": {
      "price": 14.43,
      "change_24h": -1.907173738773343,
      "volume_24h": 688978335.1497769
    }
  }
}