{
  "timestamp": "2026-06-19T23:12:45.967118Z",
  "source": "CoinGecko API",
  "prices": {
    "BTC/USDC": {
      "price": 63221,
      "change_24h": 0.7565931152971183,
      "volume_24h": 22827306748.428524
    },
    "ETH/USDC": {
      "price": 1704.14,
      "change_24h": 0.07921142797069826,
      "volume_24h": 8133885530.991519
    },
    "BNB/USDC": {
      "price": 580.02,
      "change_24h": 0.535630190069962,
      "volume_24h": 811322481.8515337
    },
    "SOL/USDC": {
      "price": 69.26,
      "change_24h": -0.120381872021838,
      "volume_24h": 1884589574.8424163
    },
    "ADA/USDC": {
      "price": 0.161236,
      "change_24h": -0.8630749017693636,
      "volume_24h": 305839814.2433563
    },
    "DOGE/USDC": {
      "price": 0.0831,
      "change_24h": -0.057489191899457004,
      "volume_24h": 419206737.5120859
    },
    "XRP/USDC": {
      "price": 1.13,
      "change_24h": -0.9750384405362232,
      "volume_24h": 1425227490.195608
    },
    "DOT/USDC": {
      "price": 0.954426,
      "change_24h": -1.3683404656599694,
      "volume_24h": 89082731.54481782
    },
    "AVAX/USDC": {
      "price": 5.91,
      "change_24h": -6.050831395696443,
      "volume_24h": 413469223.46327686
    },
    "LINK/USDC": {
      "price": 7.91,
      "change_24h": -0.6981246851820142,
      "volume_24h": 211312243.8531212
    }
  }
}