{
  "timestamp": "2026-02-01T14:43:43.202051Z",
  "source": "CoinGecko API",
  "prices": {
    "BTC/USDC": {
      "price": 77614,
      "change_24h": -4.106881449599826,
      "volume_24h": 80522590893.73755
    },
    "ETH/USDC": {
      "price": 2346.96,
      "change_24h": -6.966103348405679,
      "volume_24h": 50138812249.41378
    },
    "BNB/USDC": {
      "price": 751.84,
      "change_24h": -6.8484098006327,
      "volume_24h": 2641186903.165006
    },
    "SOL/USDC": {
      "price": 102.37,
      "change_24h": -6.3920709661040895,
      "volume_24h": 9416617599.80527
    },
    "ADA/USDC": {
      "price": 0.290286,
      "change_24h": -2.056467781363057,
      "volume_24h": 1208293653.0264444
    },
    "DOGE/USDC": {
      "price": 0.104479,
      "change_24h": -1.9572655854426766,
      "volume_24h": 2620729785.1456275
    },
    "XRP/USDC": {
      "price": 1.61,
      "change_24h": -1.2419759566737114,
      "volume_24h": 6549489465.442604
    },
    "DOT/USDC": {
      "price": 1.51,
      "change_24h": -1.8098683779086262,
      "volume_24h": 249714450.51707432
    },
    "AVAX/USDC": {
      "price": 9.94,
      "change_24h": -1.3450292312895344,
      "volume_24h": 657403335.2775538
    },
    "LINK/USDC": {
      "price": 9.65,
      "change_24h": -3.099496330673537,
      "volume_24h": 902194672.0910945
    }
  }
}