{
  "timestamp": "2026-05-06T10:01:10.475481Z",
  "source": "CoinGecko API",
  "prices": {
    "BTC/USDC": {
      "price": 81969,
      "change_24h": 1.7760679743105117,
      "volume_24h": 42874951370.15684
    },
    "ETH/USDC": {
      "price": 2411.84,
      "change_24h": 1.8355863765759952,
      "volume_24h": 18666784550.849285
    },
    "BNB/USDC": {
      "price": 646.83,
      "change_24h": 3.203617026234108,
      "volume_24h": 1421585692.1345437
    },
    "SOL/USDC": {
      "price": 89.43,
      "change_24h": 5.892134426556385,
      "volume_24h": 4356015635.283494
    },
    "ADA/USDC": {
      "price": 0.273049,
      "change_24h": 6.087274434297648,
      "volume_24h": 582870371.0297225
    },
    "DOGE/USDC": {
      "price": 0.116339,
      "change_24h": 4.7929658453813575,
      "volume_24h": 2253878183.0388837
    },
    "XRP/USDC": {
      "price": 1.45,
      "change_24h": 3.2947460727481124,
      "volume_24h": 2380930460.5280666
    },
    "DOT/USDC": {
      "price": 1.33,
      "change_24h": 5.9663431167747305,
      "volume_24h": 187062450.19477728
    },
    "AVAX/USDC": {
      "price": 9.72,
      "change_24h": 4.1119869148057,
      "volume_24h": 290423607.1440964
    },
    "LINK/USDC": {
      "price": 10.15,
      "change_24h": 5.680555177834455,
      "volume_24h": 547685353.5070456
    }
  }
}