{
  "timestamp": "2026-03-21T14:02:16.829520Z",
  "source": "CoinGecko API",
  "prices": {
    "BTC/USDC": {
      "price": 70761,
      "change_24h": 1.2936608867887933,
      "volume_24h": 28880532391.461723
    },
    "ETH/USDC": {
      "price": 2155.72,
      "change_24h": 1.3709882494846166,
      "volume_24h": 11878069803.683498
    },
    "BNB/USDC": {
      "price": 643.79,
      "change_24h": 0.9285221619728237,
      "volume_24h": 703921338.7763207
    },
    "SOL/USDC": {
      "price": 90.03,
      "change_24h": 1.2458325326962525,
      "volume_24h": 2172882785.6528425
    },
    "ADA/USDC": {
      "price": 0.264256,
      "change_24h": -0.6310442748789946,
      "volume_24h": 290143038.87658507
    },
    "DOGE/USDC": {
      "price": 0.093702,
      "change_24h": 0.28968156909526765,
      "volume_24h": 504111620.4467145
    },
    "XRP/USDC": {
      "price": 1.44,
      "change_24h": 0.0648376103999541,
      "volume_24h": 1459165488.7933357
    },
    "DOT/USDC": {
      "price": 1.49,
      "change_24h": -2.4569920959898326,
      "volume_24h": 129722352.13984567
    },
    "AVAX/USDC": {
      "price": 9.5,
      "change_24h": 0.36773042436409265,
      "volume_24h": 213037334.81865838
    },
    "LINK/USDC": {
      "price": 9.09,
      "change_24h": 0.7791824314592078,
      "volume_24h": 255727092.56598297
    }
  }
}