{
  "timestamp": "2026-03-21T11:57:11.589442Z",
  "source": "CoinGecko API",
  "prices": {
    "BTC/USDC": {
      "price": 70606,
      "change_24h": 0.21509805586673883,
      "volume_24h": 30254427092.973003
    },
    "ETH/USDC": {
      "price": 2155.81,
      "change_24h": 0.707544631507006,
      "volume_24h": 12437324585.213963
    },
    "BNB/USDC": {
      "price": 643.67,
      "change_24h": 0.36708680353850803,
      "volume_24h": 769620889.2489343
    },
    "SOL/USDC": {
      "price": 89.91,
      "change_24h": 1.035359678458071,
      "volume_24h": 2375771066.9262037
    },
    "ADA/USDC": {
      "price": 0.264411,
      "change_24h": -1.1428422456177993,
      "volume_24h": 297327303.11069745
    },
    "DOGE/USDC": {
      "price": 0.093957,
      "change_24h": 0.00398436299463402,
      "volume_24h": 560430056.9292208
    },
    "XRP/USDC": {
      "price": 1.44,
      "change_24h": -0.1330106399345017,
      "volume_24h": 1466082970.0098789
    },
    "DOT/USDC": {
      "price": 1.49,
      "change_24h": -2.348810564674035,
      "volume_24h": 135116711.609165
    },
    "AVAX/USDC": {
      "price": 9.5,
      "change_24h": 0.010298460881895252,
      "volume_24h": 227955381.28718898
    },
    "LINK/USDC": {
      "price": 9.1,
      "change_24h": 0.2494224508558982,
      "volume_24h": 279431344.99284124
    }
  }
}