{
  "timestamp": "2025-11-15T20:15:18.607575Z",
  "source": "CoinGecko API",
  "prices": {
    "BTC/USDC": {
      "price": 95820,
      "change_24h": 0.40639344439176844,
      "volume_24h": 61643485399.44121
    },
    "ETH/USDC": {
      "price": 3196.44,
      "change_24h": 0.17879497085520862,
      "volume_24h": 21626190703.68732
    },
    "BNB/USDC": {
      "price": 939.1,
      "change_24h": 1.0693925861306992,
      "volume_24h": 1190270313.3771465
    },
    "SOL/USDC": {
      "price": 141.69,
      "change_24h": -0.6701518455224985,
      "volume_24h": 3776694563.083765
    },
    "ADA/USDC": {
      "price": 0.506819,
      "change_24h": -1.5214382109221665,
      "volume_24h": 973400196.8827963
    },
    "DOGE/USDC": {
      "price": 0.163705,
      "change_24h": 0.5668027934914782,
      "volume_24h": 1426362106.408545
    },
    "XRP/USDC": {
      "price": 2.26,
      "change_24h": -1.9874124720290574,
      "volume_24h": 3151876679.2030535
    },
    "DOT/USDC": {
      "price": 2.86,
      "change_24h": -0.50731619357494,
      "volume_24h": 230834978.13576418
    },
    "AVAX/USDC": {
      "price": 15.69,
      "change_24h": 0.5583700695639647,
      "volume_24h": 334150161.4363486
    },
    "LINK/USDC": {
      "price": 14.19,
      "change_24h": -0.18998116209352414,
      "volume_24h": 562735180.6190007
    }
  }
}