{
  "timestamp": "2026-01-26T17:01:08.075022Z",
  "source": "CoinGecko API",
  "prices": {
    "BTC/USDC": {
      "price": 87522,
      "change_24h": -0.450525671078332,
      "volume_24h": 59311652494.80943
    },
    "ETH/USDC": {
      "price": 2897.98,
      "change_24h": 0.145834852177022,
      "volume_24h": 36577003841.860054
    },
    "BNB/USDC": {
      "price": 872.07,
      "change_24h": 0.28541943447611323,
      "volume_24h": 1327898008.2642777
    },
    "SOL/USDC": {
      "price": 124.36,
      "change_24h": 1.450879747343713,
      "volume_24h": 7014253182.526598
    },
    "ADA/USDC": {
      "price": 0.353171,
      "change_24h": 2.80284139966952,
      "volume_24h": 602922664.3065363
    },
    "DOGE/USDC": {
      "price": 0.122677,
      "change_24h": 1.596203728265681,
      "volume_24h": 1316364867.1265798
    },
    "XRP/USDC": {
      "price": 1.92,
      "change_24h": 3.7670155496869446,
      "volume_24h": 3718868861.3640127
    },
    "DOT/USDC": {
      "price": 1.88,
      "change_24h": 1.8465383361755634,
      "volume_24h": 143241708.6975724
    },
    "AVAX/USDC": {
      "price": 11.76,
      "change_24h": 0.9536779851574276,
      "volume_24h": 352136550.928706
    },
    "LINK/USDC": {
      "price": 11.95,
      "change_24h": 1.3014365919636528,
      "volume_24h": 480791513.0786006
    }
  }
}