{
  "timestamp": "2026-03-04T20:48:12.196772Z",
  "source": "CoinGecko API",
  "prices": {
    "BTC/USDC": {
      "price": 73529,
      "change_24h": 7.5313312906530285,
      "volume_24h": 79171336980.28513
    },
    "ETH/USDC": {
      "price": 2173.5,
      "change_24h": 9.685280142264684,
      "volume_24h": 33648327162.289307
    },
    "BNB/USDC": {
      "price": 662.83,
      "change_24h": 4.768641091685793,
      "volume_24h": 1580619314.5066347
    },
    "SOL/USDC": {
      "price": 93.63,
      "change_24h": 10.037374554042254,
      "volume_24h": 7498070198.584528
    },
    "ADA/USDC": {
      "price": 0.281948,
      "change_24h": 7.437252761513586,
      "volume_24h": 957751528.6393404
    },
    "DOGE/USDC": {
      "price": 0.102925,
      "change_24h": 15.324267772818922,
      "volume_24h": 2482340105.4358273
    },
    "XRP/USDC": {
      "price": 1.46,
      "change_24h": 7.707043307742759,
      "volume_24h": 4091941432.6165376
    },
    "DOT/USDC": {
      "price": 1.56,
      "change_24h": 1.7701348371119938,
      "volume_24h": 203869446.605842
    },
    "AVAX/USDC": {
      "price": 9.65,
      "change_24h": 5.237188891520625,
      "volume_24h": 454594722.0227885
    },
    "LINK/USDC": {
      "price": 9.55,
      "change_24h": 8.549399574992492,
      "volume_24h": 514021758.03805166
    }
  }
}