{
  "timestamp": "2026-02-21T16:53:54.099117Z",
  "source": "CoinGecko API",
  "prices": {
    "BTC/USDC": {
      "price": 68330,
      "change_24h": 1.027493020207558,
      "volume_24h": 32174843802.28675
    },
    "ETH/USDC": {
      "price": 1988.44,
      "change_24h": 1.2688749836402293,
      "volume_24h": 16819735771.392527
    },
    "BNB/USDC": {
      "price": 625.93,
      "change_24h": 1.1398142964408153,
      "volume_24h": 823602083.8577971
    },
    "SOL/USDC": {
      "price": 86.2,
      "change_24h": 2.4739954024132405,
      "volume_24h": 2713911374.3341503
    },
    "ADA/USDC": {
      "price": 0.280963,
      "change_24h": -1.8858244388474512,
      "volume_24h": 339765360.01677877
    },
    "DOGE/USDC": {
      "price": 0.099729,
      "change_24h": -0.6851415667197985,
      "volume_24h": 650591537.0031555
    },
    "XRP/USDC": {
      "price": 1.44,
      "change_24h": 1.0185994009080257,
      "volume_24h": 1816724999.0412717
    },
    "DOT/USDC": {
      "price": 1.36,
      "change_24h": 1.560899550397101,
      "volume_24h": 113563876.17251186
    },
    "AVAX/USDC": {
      "price": 9.23,
      "change_24h": 1.2470669212097556,
      "volume_24h": 205566307.1967566
    },
    "LINK/USDC": {
      "price": 8.9,
      "change_24h": 0.403203577144738,
      "volume_24h": 279328565.22637874
    }
  }
}