{
  "timestamp": "2025-12-16T15:43:44.588857Z",
  "source": "CoinGecko API",
  "prices": {
    "BTC/USDC": {
      "price": 87174,
      "change_24h": -0.002085132451950688,
      "volume_24h": 55530058957.90842
    },
    "ETH/USDC": {
      "price": 2933.98,
      "change_24h": -2.3576702687104145,
      "volume_24h": 28854787240.74333
    },
    "BNB/USDC": {
      "price": 869.52,
      "change_24h": 1.4036068920684621,
      "volume_24h": 1899618601.0142903
    },
    "SOL/USDC": {
      "price": 128.07,
      "change_24h": 0.6854843786745322,
      "volume_24h": 5474680887.353444
    },
    "ADA/USDC": {
      "price": 0.385811,
      "change_24h": 0.3636782883830172,
      "volume_24h": 680827538.0208778
    },
    "DOGE/USDC": {
      "price": 0.131425,
      "change_24h": 0.7128464806194158,
      "volume_24h": 1290533505.9785638
    },
    "XRP/USDC": {
      "price": 1.93,
      "change_24h": 0.2689531526660191,
      "volume_24h": 3913291254.5236197
    },
    "DOT/USDC": {
      "price": 1.9,
      "change_24h": 0.6518510208921475,
      "volume_24h": 213538886.52172577
    },
    "AVAX/USDC": {
      "price": 12.19,
      "change_24h": -2.590679572251809,
      "volume_24h": 420861276.7353574
    },
    "LINK/USDC": {
      "price": 12.89,
      "change_24h": 0.5625243439167845,
      "volume_24h": 702275150.8554192
    }
  }
}