{
  "timestamp": "2025-12-08T07:52:17.829725Z",
  "source": "CoinGecko API",
  "prices": {
    "BTC/USDC": {
      "price": 91548,
      "change_24h": 2.4467608022559992,
      "volume_24h": 40284415205.90304
    },
    "ETH/USDC": {
      "price": 3130.88,
      "change_24h": 3.0956564797308883,
      "volume_24h": 25901366213.948074
    },
    "BNB/USDC": {
      "price": 903.11,
      "change_24h": 1.2458113527095669,
      "volume_24h": 1566537737.7912717
    },
    "SOL/USDC": {
      "price": 135.72,
      "change_24h": 2.693956725014143,
      "volume_24h": 5045058938.153952
    },
    "ADA/USDC": {
      "price": 0.429075,
      "change_24h": 2.4804373694228956,
      "volume_24h": 655980208.222934
    },
    "DOGE/USDC": {
      "price": 0.142097,
      "change_24h": 1.786236869841334,
      "volume_24h": 1198423197.4227061
    },
    "XRP/USDC": {
      "price": 2.09,
      "change_24h": 2.6784045994136174,
      "volume_24h": 3083441512.799923
    },
    "DOT/USDC": {
      "price": 2.14,
      "change_24h": 0.39109086318638003,
      "volume_24h": 197393738.00562435
    },
    "AVAX/USDC": {
      "price": 13.69,
      "change_24h": 2.1431729555947987,
      "volume_24h": 402302766.29911715
    },
    "LINK/USDC": {
      "price": 14.02,
      "change_24h": 0.6772652582314154,
      "volume_24h": 713146402.6297591
    }
  }
}