{
  "timestamp": "2025-11-13T08:47:40.424950Z",
  "source": "CoinGecko API",
  "prices": {
    "BTC/USDC": {
      "price": 103736,
      "change_24h": -0.2726311319840475,
      "volume_24h": 75281285062.51178
    },
    "ETH/USDC": {
      "price": 3543.67,
      "change_24h": 2.090288787032993,
      "volume_24h": 37451717457.63142
    },
    "BNB/USDC": {
      "price": 966.15,
      "change_24h": 0.24743002574273407,
      "volume_24h": 1628935352.6780787
    },
    "SOL/USDC": {
      "price": 156.21,
      "change_24h": -0.8866272746295703,
      "volume_24h": 6272222324.9882555
    },
    "ADA/USDC": {
      "price": 0.568344,
      "change_24h": 0.41037152781126146,
      "volume_24h": 1011487063.4138261
    },
    "DOGE/USDC": {
      "price": 0.176123,
      "change_24h": 1.1604993480683425,
      "volume_24h": 2001214037.4566066
    },
    "XRP/USDC": {
      "price": 2.51,
      "change_24h": 4.050927791446863,
      "volume_24h": 5579997446.364926
    },
    "DOT/USDC": {
      "price": 3.0,
      "change_24h": -3.865506930795158,
      "volume_24h": 291861582.2794284
    },
    "AVAX/USDC": {
      "price": 17.51,
      "change_24h": 0.5025871720536158,
      "volume_24h": 516535488.32306033
    },
    "LINK/USDC": {
      "price": 15.92,
      "change_24h": 1.80228418860203,
      "volume_24h": 916141978.7423466
    }
  }
}