{
  "timestamp": "2025-11-22T17:40:14.886096Z",
  "source": "CoinGecko API",
  "prices": {
    "BTC/USDC": {
      "price": 84551,
      "change_24h": -0.6843449474755352,
      "volume_24h": 56402383464.89098
    },
    "ETH/USDC": {
      "price": 2749.23,
      "change_24h": -1.3756007362425087,
      "volume_24h": 20486239224.13748
    },
    "BNB/USDC": {
      "price": 827.71,
      "change_24h": -0.7039537634299077,
      "volume_24h": 1980354086.0892403
    },
    "SOL/USDC": {
      "price": 127.57,
      "change_24h": -1.7847939939996837,
      "volume_24h": 4580254407.779938
    },
    "ADA/USDC": {
      "price": 0.400788,
      "change_24h": -3.6091357595920672,
      "volume_24h": 662544793.1928555
    },
    "DOGE/USDC": {
      "price": 0.139122,
      "change_24h": -2.6643034708661304,
      "volume_24h": 1820699410.1894972
    },
    "XRP/USDC": {
      "price": 1.93,
      "change_24h": -2.654626080753751,
      "volume_24h": 4164423592.891215
    },
    "DOT/USDC": {
      "price": 2.29,
      "change_24h": -5.52250225417602,
      "volume_24h": 187134251.72386366
    },
    "AVAX/USDC": {
      "price": 13.23,
      "change_24h": -1.3070140222034556,
      "volume_24h": 445047271.04210496
    },
    "LINK/USDC": {
      "price": 12.02,
      "change_24h": -2.2961906293397685,
      "volume_24h": 632594845.9069612
    }
  }
}