{
  "timestamp": "2026-01-05T23:40:03.231941Z",
  "source": "CoinGecko API",
  "prices": {
    "BTC/USDC": {
      "price": 93890,
      "change_24h": 2.7929504989374276,
      "volume_24h": 59407296047.74769
    },
    "ETH/USDC": {
      "price": 3226.95,
      "change_24h": 2.7656759332472918,
      "volume_24h": 28122890254.4274
    },
    "BNB/USDC": {
      "price": 911.26,
      "change_24h": 1.925755075439076,
      "volume_24h": 1531592870.748671
    },
    "SOL/USDC": {
      "price": 138.26,
      "change_24h": 3.1251204796868612,
      "volume_24h": 5827344091.767896
    },
    "ADA/USDC": {
      "price": 0.422952,
      "change_24h": 5.792393755619287,
      "volume_24h": 915245021.5260234
    },
    "DOGE/USDC": {
      "price": 0.152201,
      "change_24h": 1.878696952100371,
      "volume_24h": 2059825449.628136
    },
    "XRP/USDC": {
      "price": 2.36,
      "change_24h": 12.856273721857855,
      "volume_24h": 6917608181.544868
    },
    "DOT/USDC": {
      "price": 2.21,
      "change_24h": 3.0860313630107297,
      "volume_24h": 213439894.39965737
    },
    "AVAX/USDC": {
      "price": 14.48,
      "change_24h": 1.297748082202471,
      "volume_24h": 496214193.48897773
    },
    "LINK/USDC": {
      "price": 13.98,
      "change_24h": 4.173559586809359,
      "volume_24h": 701972383.1544954
    }
  }
}