{
  "timestamp": "2025-12-07T21:38:10.614200Z",
  "source": "CoinGecko API",
  "prices": {
    "BTC/USDC": {
      "price": 90874,
      "change_24h": 1.586947526936187,
      "volume_24h": 31214340133.81747
    },
    "ETH/USDC": {
      "price": 3125.38,
      "change_24h": 2.6923620126524566,
      "volume_24h": 19149686331.986416
    },
    "BNB/USDC": {
      "price": 901.72,
      "change_24h": 0.8250128820255828,
      "volume_24h": 1300835999.3101294
    },
    "SOL/USDC": {
      "price": 135.05,
      "change_24h": 2.008986756202455,
      "volume_24h": 3890719000.858384
    },
    "ADA/USDC": {
      "price": 0.427384,
      "change_24h": 3.1491957342409664,
      "volume_24h": 577741302.0672491
    },
    "DOGE/USDC": {
      "price": 0.141206,
      "change_24h": 0.9000137959737876,
      "volume_24h": 980622683.1458362
    },
    "XRP/USDC": {
      "price": 2.07,
      "change_24h": 1.7076946190941165,
      "volume_24h": 2553404850.973962
    },
    "DOT/USDC": {
      "price": 2.13,
      "change_24h": -0.3977668142339039,
      "volume_24h": 161935560.92481783
    },
    "AVAX/USDC": {
      "price": 13.72,
      "change_24h": 2.449308161543084,
      "volume_24h": 353731572.3072147
    },
    "LINK/USDC": {
      "price": 14.0,
      "change_24h": 0.240923634070922,
      "volume_24h": 579202740.7967563
    }
  }
}